Airm/LinearRegression.py
Airm/Non_LinearRegression.py
Airm/__init__.py
Airm-1.0.3.dist-info/LICENSE
Airm-1.0.3.dist-info/METADATA
Airm-1.0.3.dist-info/WHEEL
Airm-1.0.3.dist-info/top_level.txt
Airm-1.0.3.dist-info/RECORD
