Metadata-Version: 2.1
Name: Airm
Version: 1.0.3
Summary: Regression Models
Home-page: UNKNOWN
Author: Ashvini Jangid
Author-email: ashvinijangid@gmail.com
License: MIT
Platform: UNKNOWN
Requires-Dist: numpy
